ibm_cloud_fail_over/__init__.py
ibm_cloud_fail_over/ibm_cloud_fail_over.py
ibm_cloud_fail_over-1.0.21.dist-info/METADATA
ibm_cloud_fail_over-1.0.21.dist-info/WHEEL
ibm_cloud_fail_over-1.0.21.dist-info/licenses/LICENSE
ibm_cloud_fail_over-1.0.21.dist-info/RECORD
