Metadata-Version: 2.4
Name: ibm_cloud_fail_over
Version: 1.0.21
Summary: Module providing IBM Fail over functions
Project-URL: Homepage, https://github.com/gampel/ibm_cloud_fail_over
Project-URL: Issues, https://github.com/gampel/ibm_cloud_fail_over/issues
Author-email: Eran Gampel <dev@gampel.net>
License-File: LICENSE
Classifier: License :: OSI Approved :: MIT License
Classifier: Operating System :: OS Independent
Classifier: Programming Language :: Python :: 3
Requires-Python: >=3.8
Requires-Dist: ibm-cloud-sdk-core
Requires-Dist: ibm-vpc
